p3d_appimage/__init__.py
p3d_appimage/p3d_appimage.py
panda3d_appimage-0.1.2.dist-info/LICENSE
panda3d_appimage-0.1.2.dist-info/METADATA
panda3d_appimage-0.1.2.dist-info/WHEEL
panda3d_appimage-0.1.2.dist-info/top_level.txt
panda3d_appimage-0.1.2.dist-info/RECORD
