Metadata-Version: 2.1
Name: panda3d-appimage
Version: 0.1.2
Summary: AppImage support for Panda3D
Home-page: https://www.ya2.it/pages/panda3d-appimage.html
Author: Flavio Calva
Author-email: f.calva@gmail.com
Project-URL: Repository, https://git.ya2.it/?p=panda3d-appimage.git
Classifier: Programming Language :: Python :: 3
Classifier: License :: OSI Approved :: BSD License
Classifier: Operating System :: POSIX :: Linux
Requires-Python: >=3.8
License-File: LICENSE
